src/__init__.py
src/wqtool.py
wqtool-0.1.1.dist-info/METADATA
wqtool-0.1.1.dist-info/WHEEL
wqtool-0.1.1.dist-info/entry_points.txt
wqtool-0.1.1.dist-info/top_level.txt
wqtool-0.1.1.dist-info/RECORD
